MANIFEST.in
README.md
VERSION
mkpipU.py
setup.py
mkpipU.egg-info/PKG-INFO
mkpipU.egg-info/SOURCES.txt
mkpipU.egg-info/dependency_links.txt
mkpipU.egg-info/entry_points.txt
mkpipU.egg-info/top_level.txt