Metadata-Version: 1.1
Name: mkpipU
Version: 0.3
Summary: pip upgrade all packages
Home-page: https://github.com/MichaelKim0407/mk-pip-upgrade-all
Author: Michael Kim
Author-email: mkim0407@gmail.com
License: MIT
Platform: UNKNOWN
Classifier: Development Status :: 3 - Alpha
Classifier: Intended Audience :: Developers
Classifier: Intended Audience :: End Users/Desktop
Classifier: License :: OSI Approved :: MIT License
Classifier: Programming Language :: Python :: 3.5
Classifier: Programming Language :: Python :: 3.6
Classifier: Topic :: Software Development :: Libraries
Classifier: Topic :: Terminals
Classifier: Topic :: Utilities
